{
    "1": {
        "exp": 1000,
        "cumm_exp": 0
    },
    "2": {
        "exp": 1325,
        "cumm_exp": 1000
    },
    "3": {
        "exp": 1700,
        "cumm_exp": 2325
    },
    "4": {
        "exp": 2150,
        "cumm_exp": 4025
    },
    "5": {
        "exp": 2625,
        "cumm_exp": 6175
    },
    "6": {
        "exp": 3150,
        "cumm_exp": 8800
    },
    "7": {
        "exp": 3725,
        "cumm_exp": 11950
    },
    "8": {
        "exp": 4350,
        "cumm_exp": 15675
    },
    "9": {
        "exp": 5000,
        "cumm_exp": 20025
    },
    "10": {
        "exp": 5700,
        "cumm_exp": 25025
    },
    "11": {
        "exp": 6450,
        "cumm_exp": 30725
    },
    "12": {
        "exp": 7225,
        "cumm_exp": 37175
    },
    "13": {
        "exp": 8050,
        "cumm_exp": 44400
    },
    "14": {
        "exp": 8925,
        "cumm_exp": 52450
    },
    "15": {
        "exp": 9825,
        "cumm_exp": 61375
    },
    "16": {
        "exp": 10750,
        "cumm_exp": 71200
    },
    "17": {
        "exp": 11725,
        "cumm_exp": 81950
    },
    "18": {
        "exp": 12725,
        "cumm_exp": 93675
    },
    "19": {
        "exp": 13775,
        "cumm_exp": 106400
    },
    "20": {
        "exp": 14875,
        "cumm_exp": 120175
    },
    "21": {
        "exp": 16800,
        "cumm_exp": 135050
    },
    "22": {
        "exp": 18000,
        "cumm_exp": 151850
    },
    "23": {
        "exp": 19250,
        "cumm_exp": 169850
    },
    "24": {
        "exp": 20550,
        "cumm_exp": 189100
    },
    "25": {
        "exp": 21875,
        "cumm_exp": 209650
    },
    "26": {
        "exp": 23250,
        "cumm_exp": 231525
    },
    "27": {
        "exp": 24650,
        "cumm_exp": 254775
    },
    "28": {
        "exp": 26100,
        "cumm_exp": 279425
    },
    "29": {
        "exp": 27575,
        "cumm_exp": 305525
    },
    "30": {
        "exp": 29100,
        "cumm_exp": 333100
    },
    "31": {
        "exp": 30650,
        "cumm_exp": 362200
    },
    "32": {
        "exp": 32250,
        "cumm_exp": 392850
    },
    "33": {
        "exp": 33875,
        "cumm_exp": 425100
    },
    "34": {
        "exp": 35550,
        "cumm_exp": 458975
    },
    "35": {
        "exp": 37250,
        "cumm_exp": 494525
    },
    "36": {
        "exp": 38975,
        "cumm_exp": 531775
    },
    "37": {
        "exp": 40750,
        "cumm_exp": 570750
    },
    "38": {
        "exp": 42575,
        "cumm_exp": 611500
    },
    "39": {
        "exp": 44425,
        "cumm_exp": 654075
    },
    "40": {
        "exp": 46300,
        "cumm_exp": 698500
    },
    "41": {
        "exp": 50625,
        "cumm_exp": 744800
    },
    "42": {
        "exp": 52700,
        "cumm_exp": 795425
    },
    "43": {
        "exp": 54775,
        "cumm_exp": 848125
    },
    "44": {
        "exp": 56900,
        "cumm_exp": 902900
    },
    "45": {
        "exp": 59075,
        "cumm_exp": 959800
    },
    "46": {
        "exp": 61275,
        "cumm_exp": 1018875
    },
    "47": {
        "exp": 63525,
        "cumm_exp": 1080150
    },
    "48": {
        "exp": 65800,
        "cumm_exp": 1143675
    },
    "49": {
        "exp": 68125,
        "cumm_exp": 1209475
    },
    "50": {
        "exp": 70475,
        "cumm_exp": 1277600
    },
    "51": {
        "exp": 76500,
        "cumm_exp": 1348075
    },
    "52": {
        "exp": 79050,
        "cumm_exp": 1424575
    },
    "53": {
        "exp": 81650,
        "cumm_exp": 1503625
    },
    "54": {
        "exp": 84275,
        "cumm_exp": 1585275
    },
    "55": {
        "exp": 86950,
        "cumm_exp": 1669550
    },
    "56": {
        "exp": 89650,
        "cumm_exp": 1756500
    },
    "57": {
        "exp": 92400,
        "cumm_exp": 1846150
    },
    "58": {
        "exp": 95175,
        "cumm_exp": 1938550
    },
    "59": {
        "exp": 98000,
        "cumm_exp": 2033725
    },
    "60": {
        "exp": 100875,
        "cumm_exp": 2131725
    },
    "61": {
        "exp": 108950,
        "cumm_exp": 2232600
    },
    "62": {
        "exp": 112050,
        "cumm_exp": 2341550
    },
    "63": {
        "exp": 115175,
        "cumm_exp": 2453600
    },
    "64": {
        "exp": 118325,
        "cumm_exp": 2568775
    },
    "65": {
        "exp": 121525,
        "cumm_exp": 2687100
    },
    "66": {
        "exp": 124775,
        "cumm_exp": 2808625
    },
    "67": {
        "exp": 128075,
        "cumm_exp": 2933400
    },
    "68": {
        "exp": 131400,
        "cumm_exp": 3061475
    },
    "69": {
        "exp": 134775,
        "cumm_exp": 3192875
    },
    "70": {
        "exp": 138175,
        "cumm_exp": 3327650
    },
    "71": {
        "exp": 148700,
        "cumm_exp": 3465825
    },
    "72": {
        "exp": 152375,
        "cumm_exp": 3614525
    },
    "73": {
        "exp": 156075,
        "cumm_exp": 3766900
    },
    "74": {
        "exp": 159825,
        "cumm_exp": 3922975
    },
    "75": {
        "exp": 163600,
        "cumm_exp": 4082800
    },
    "76": {
        "exp": 167425,
        "cumm_exp": 4246400
    },
    "77": {
        "exp": 171300,
        "cumm_exp": 4413825
    },
    "78": {
        "exp": 175225,
        "cumm_exp": 4585125
    },
    "79": {
        "exp": 179175,
        "cumm_exp": 4760350
    },
    "80": {
        "exp": 183175,
        "cumm_exp": 4939525
    },
    "81": {
        "exp": 216225,
        "cumm_exp": 5122700
    },
    "82": {
        "exp": 243025,
        "cumm_exp": 5338925
    },
    "83": {
        "exp": 273100,
        "cumm_exp": 5581950
    },
    "84": {
        "exp": 306800,
        "cumm_exp": 5855050
    },
    "85": {
        "exp": 344600,
        "cumm_exp": 6161850
    },
    "86": {
        "exp": 386950,
        "cumm_exp": 6506450
    },
    "87": {
        "exp": 434425,
        "cumm_exp": 6893400
    },
    "88": {
        "exp": 487625,
        "cumm_exp": 7327825
    },
    "89": {
        "exp": 547200,
        "cumm_exp": 7815450
    },
    "90": {
        "exp": 0,
        "cumm_exp": 8362650
    }
}